LICENSE
README.md
pyproject.toml
procstat/__init__.py
procstat/base.py
procstat/export_prometheus.py
procstat/py.typed
procstat/stat.py
procstat.egg-info/PKG-INFO
procstat.egg-info/SOURCES.txt
procstat.egg-info/dependency_links.txt
procstat.egg-info/top_level.txt
tests/test_nothing.py
tests/test_stat.py