Metadata-Version: 2.1
Name: procstat
Version: 0.0.8
Summary: Tool to count runtime metrics
Author-email: Gregory Petukhov <lorien@lorien.name>
License: The MIT License (MIT)
Project-URL: homepage, http://github.com/lorien/procstat
Keywords: stat,stats,statistics,metrics
Classifier: Typing :: Typed
Classifier: Programming Language :: Python
Classifier: Programming Language :: Python :: 3
Classifier: Programming Language :: Python :: 3.8
Classifier: Programming Language :: Python :: 3.9
Classifier: Programming Language :: Python :: 3.10
Classifier: Programming Language :: Python :: 3.11
Classifier: License :: OSI Approved :: MIT License
Classifier: Development Status :: 4 - Beta
Classifier: Intended Audience :: Developers
Classifier: Operating System :: OS Independent
Classifier: Topic :: Software Development :: Libraries :: Python Modules
Requires-Python: >=3.8
License-File: LICENSE
